LICENSE.txt
MANIFEST.in
README.rst
setup.py
djangocms_translations/__init__.py
djangocms_translations/admin.py
djangocms_translations/apps.py
djangocms_translations/cms_renderer.py
djangocms_translations/cms_toolbars.py
djangocms_translations/conf.py
djangocms_translations/forms.py
djangocms_translations/models.py
djangocms_translations/tasks.py
djangocms_translations/utils.py
djangocms_translations/views.py
djangocms_translations.egg-info/PKG-INFO
djangocms_translations.egg-info/SOURCES.txt
djangocms_translations.egg-info/dependency_links.txt
djangocms_translations.egg-info/not-zip-safe
djangocms_translations.egg-info/requires.txt
djangocms_translations.egg-info/top_level.txt
djangocms_translations/migrations/0001_initial.py
djangocms_translations/migrations/0002_auto_20171122_1019.py
djangocms_translations/migrations/0003_archivedplaceholder_archivedplugin.py
djangocms_translations/migrations/0004_auto_20171219_1209.py
djangocms_translations/migrations/0005_auto_20180208_1756.py
djangocms_translations/migrations/0006_translationimport.py
djangocms_translations/migrations/0007_translationrequest_provider_order_name.py
djangocms_translations/migrations/0008_auto_20180524_1354.py
djangocms_translations/migrations/0009_auto_20181220_0902.py
djangocms_translations/migrations/__init__.py
djangocms_translations/providers/__init__.py
djangocms_translations/providers/base.py
djangocms_translations/providers/supertext.py
djangocms_translations/templates/admin/djangocms_translations/translationrequest/bulk_create_step_1.html
djangocms_translations/templates/admin/djangocms_translations/translationrequest/bulk_create_step_2.html
djangocms_translations/templates/admin/djangocms_translations/translationrequest/bulk_create_step_3.html
djangocms_translations/templates/admin/djangocms_translations/translationrequest/change_form.html
djangocms_translations/templates/djangocms_translations/adjust_import_data.html
djangocms_translations/templates/djangocms_translations/base.html
djangocms_translations/templates/djangocms_translations/choose_quote.html
djangocms_translations/templates/djangocms_translations/create_request.html
djangocms_translations/templates/djangocms_translations/import_confirmation.html
