Metadata-Version: 1.1
Name: djangocms-translations
Version: 1.4.0
Summary: Send django CMS content for translation to 3rd party providers.
Home-page: https://github.com/divio/djangocms-translations
Author: Divio AG
Author-email: info@divio.ch
License: BSD
Platform: UNKNOWN
Classifier: Development Status :: 4 - Beta
Classifier: Environment :: Web Environment
Classifier: Framework :: Django
Classifier: Intended Audience :: Developers
Classifier: License :: OSI Approved :: BSD License
Classifier: Operating System :: OS Independent
Classifier: Programming Language :: Python
Classifier: Topic :: Internet :: WWW/HTTP :: Dynamic Content
Classifier: Topic :: Software Development
Classifier: Topic :: Software Development :: Libraries :: Application Frameworks
